langchain_google_vertexai/__init__.py
langchain_google_vertexai/_anthropic_parsers.py
langchain_google_vertexai/_anthropic_utils.py
langchain_google_vertexai/_base.py
langchain_google_vertexai/_enums.py
langchain_google_vertexai/_image_utils.py
langchain_google_vertexai/_utils.py
langchain_google_vertexai/callbacks.py
langchain_google_vertexai/chains.py
langchain_google_vertexai/chat_models.py
langchain_google_vertexai/embeddings.py
langchain_google_vertexai/evaluators/__init__.py
langchain_google_vertexai/evaluators/_core.py
langchain_google_vertexai/evaluators/evaluation.py
langchain_google_vertexai/functions_utils.py
langchain_google_vertexai/gemma.py
langchain_google_vertexai/llms.py
langchain_google_vertexai/model_garden.py
langchain_google_vertexai/model_garden_maas/__init__.py
langchain_google_vertexai/model_garden_maas/_base.py
langchain_google_vertexai/model_garden_maas/llama.py
langchain_google_vertexai/model_garden_maas/mistral.py
langchain_google_vertexai/py.typed
langchain_google_vertexai/utils.py
langchain_google_vertexai/vectorstores/__init__.py
langchain_google_vertexai/vectorstores/_sdk_manager.py
langchain_google_vertexai/vectorstores/_searcher.py
langchain_google_vertexai/vectorstores/_utils.py
langchain_google_vertexai/vectorstores/document_storage.py
langchain_google_vertexai/vectorstores/vectorstores.py
langchain_google_vertexai/vision_models.py
gigachain_google_vertexai-2.0.0.dist-info/LICENSE
gigachain_google_vertexai-2.0.0.dist-info/METADATA
gigachain_google_vertexai-2.0.0.dist-info/WHEEL
gigachain_google_vertexai-2.0.0.dist-info/RECORD
