Metadata-Version: 2.1
Name: gigachain-google-vertexai
Version: 2.0.0
Summary: An integration package connecting Google VertexAI and GigaChain
Home-page: https://github.com/langchain-ai/langchain-google
License: MIT
Requires-Python: >=3.9,<4.0
Classifier: License :: OSI Approved :: MIT License
Classifier: Programming Language :: Python :: 3
Classifier: Programming Language :: Python :: 3.9
Classifier: Programming Language :: Python :: 3.10
Classifier: Programming Language :: Python :: 3.11
Classifier: Programming Language :: Python :: 3.12
Provides-Extra: anthropic
Provides-Extra: mistral
Requires-Dist: anthropic[vertexai] (>=0.30.0,<1) ; extra == "anthropic"
Requires-Dist: gigachain-core (>=0.2.38post2,<0.4)
Requires-Dist: google-cloud-aiplatform (>=1.56.0,<2.0.0)
Requires-Dist: google-cloud-storage (>=2.17.0,<3.0.0)
Requires-Dist: httpx (>=0.27.0,<0.28.0)
Requires-Dist: httpx-sse (>=0.4.0,<0.5.0)
Requires-Dist: langchain-mistralai (>=0.2.0,<1)
Requires-Dist: pydantic (>=2,<3)
Project-URL: Repository, https://github.com/langchain-ai/langchain-google
Project-URL: Source Code, https://github.com/langchain-ai/langchain-google/tree/main/libs/vertexai
